cms/__init__.py
cms/aes_utils.py
cms/http_utils.py
tests/__init__.py
tests/test_http_utils.py
cms_crypto-1.0.2.dist-info/METADATA
cms_crypto-1.0.2.dist-info/WHEEL
cms_crypto-1.0.2.dist-info/top_level.txt
cms_crypto-1.0.2.dist-info/RECORD
