Metadata-Version: 2.1
Name: cms-crypto
Version: 1.0.2
Summary: CMS decryption helper package
Home-page: https://github.com/fin1te/
Author: Rishabh Mehta
Author-email: Rishabh2.Mehta@ril.com
Requires-Dist: requests
Requires-Dist: loguru
Requires-Dist: pycryptodome
Requires-Dist: setuptools
